LICENSE
MANIFEST.in
setup.cfg
setup.py
shipping.xml
urls.xml
./__init__.py
./methods.py
./shipping.py
./shipping.xml
./tryton.cfg
./urls.xml
./tests/__init__.py
./tests/test_shipping.py
./tests/xml_test_runner.py
trytond_nereid_shipping.egg-info/PKG-INFO
trytond_nereid_shipping.egg-info/SOURCES.txt
trytond_nereid_shipping.egg-info/dependency_links.txt
trytond_nereid_shipping.egg-info/entry_points.txt
trytond_nereid_shipping.egg-info/not-zip-safe
trytond_nereid_shipping.egg-info/requires.txt
trytond_nereid_shipping.egg-info/top_level.txt