Metadata-Version: 1.1
Name: trytond-nereid-shipping
Version: 3.0.1.0
Summary: API to facilitate multiple shipping methods to integrate
Home-page: http://www.openlabs.co.in/
Author: Openlabs Technologies & Consulting (P) LTD
Author-email: info@openlabs.co.in
License: GPL-3
Platform: UNKNOWN
Classifier: Development Status :: 5 - Production/Stable
Classifier: Environment :: Plugins
Classifier: Intended Audience :: Developers
Classifier: Intended Audience :: Financial and Insurance Industry
Classifier: Intended Audience :: Legal Industry
Classifier: Intended Audience :: Manufacturing
Classifier: License :: OSI Approved :: GNU General Public License v3 (GPLv3)
Classifier: Natural Language :: English
Classifier: Operating System :: OS Independent
Classifier: Programming Language :: Python
Classifier: Framework :: Tryton
Classifier: Topic :: Office/Business
